{
  "__type__": "cc.SpriteFrame",
  "content": {
    "name": "slot-icon-effect-6",
    "atlas": "a685e7aa-258c-4633-92cb-ba3797ffb1bb",
    "rect": {
      "x": 290,
      "y": 145,
      "width": 145,
      "height": 145
    },
    "offset": {
      "x": 0,
      "y": 0
    },
    "originalSize": {
      "width": 145,
      "height": 145
    },
    "rotated": false,
    "capInsets": [
      0,
      0,
      0,
      0
    ],
    "vertices": {
      "rawPosition": [],
      "indexes": [],
      "uv": [],
      "nuv": [],
      "minPos": {
        "x": 0,
        "y": 0,
        "z": 0
      },
      "maxPos": {
        "x": 0,
        "y": 0,
        "z": 0
      }
    },
    "texture": "5752cc03-fd18-41b8-88c0-a65194cca8c0@6c48a",
    "packable": true,
    "pixelsToUnit": 100,
    "pivot": {
      "x": 0.5,
      "y": 0.5
    },
    "meshType": 0
  }
}